Metadata-Version: 2.1
Name: alice-skills-maneger
Version: 0.0.3
Summary: Alice Skills Manager
Home-page: https://github.com/Alice-IA/alice-skills-manager
Author: Alice-IA
Author-email: yuiassistant@gmail.com
License: Apache-2.0
Classifier: Development Status :: 4 - Beta
Classifier: Intended Audience :: Developers
Classifier: License :: OSI Approved :: Apache Software License
Classifier: Programming Language :: Python :: 3.6
Classifier: Programming Language :: Python :: 3.7
Classifier: Programming Language :: Python :: 3.8
Classifier: Programming Language :: Python :: 3.9
Requires-Python: >=3.6
